vigenere/__init__.py
vigenere/__main__.py
vigenere/alphabet.py
vigenere/cipher.py
vigenere/cli.py
vigenere/errors.py
vigenere/pwinput.py
vigenere_py-0.2.1.dist-info/LICENSE
vigenere_py-0.2.1.dist-info/METADATA
vigenere_py-0.2.1.dist-info/WHEEL
vigenere_py-0.2.1.dist-info/entry_points.txt
vigenere_py-0.2.1.dist-info/RECORD
