Metadata-Version: 2.1
Name: vigenere-py
Version: 0.2.1
Summary: Vigenere cipher encryption for Python
Home-page: https://github.com/ab/vigenere-py
License: MIT
Author: Andy Brody
Author-email: git@abrody.com
Requires-Python: >=3.8,<4.0
Classifier: Development Status :: 3 - Alpha
Classifier: License :: OSI Approved :: MIT License
Classifier: Programming Language :: Python :: 3
Classifier: Programming Language :: Python :: 3.8
Classifier: Programming Language :: Python :: 3.9
Classifier: Programming Language :: Python :: 3.10
Classifier: Programming Language :: Python :: 3.11
Classifier: Programming Language :: Python :: 3.12
Classifier: Topic :: Security :: Cryptography
Requires-Dist: click (>=8.1.7,<9.0.0)
Requires-Dist: strictyaml (>=1.7.3,<2.0.0)
Project-URL: Issues, https://github.com/ab/vigenere-py/issues
Project-URL: Releases, https://github.com/ab/vigenere-py/releases
